Workbook

Sheet Operating Budgets
C1: Sales Budget
C2: 45985 | D2: 46015 | E2: 45682 | F2: 45713 | G2: 45741 | H2: 45772 | I2: 45802 | J2: 45833 | K2: 45863 | L2: 45894 | M2: 45925 | N2: 45955 | O2: 45986 | P2: 46016 | Q2: Jan | R2: Feb | S2: Total 2025
B3: Expected unit sales | C3: =C9 -> 8800 | D3: =D9 -> 9720 | E3: =E9 -> 10540 | F3: =F9 -> 14280 | G3: =G9 -> 22200 | H3: =H9 -> 24900 | I3: =I9 -> 29280 | J3: =J9 -> 37260 | ... Q3: =Q9 -> 11400 | S3: =SUM(E3:P3) -> 263080
B4: Unit selling price | C4: 409 | D4: 409 | E4: 409 | F4: 409 | G4: 409 | H4: 409 | I4: 409 | J4: 409 | K4: 409 | L4: 409 | M4: =M5/M3 -> 360 | N4: 409 | O4: 409 | P4: 409 | Q4: 409 | S4: =SUM(E4:P4) -> 4859
B5: Total sales | C5: =C4*C3 -> 3599200 | D5: =D4*D3 -> 3975480 | E5: =E4*E3 -> 4310860 | F5: =F4*F3 -> 5840520 | G5: =G4*G3 -> 9079800 | H5: =H4*H3 -> 10184100 | I5: =I4*I3 -> 11975520 | J5: =J4*J3 -> 15239340 | ... L5: =L4*L3 -> 9603320 | M5: 14040000 | N5: =N4*N3 -> 6535820 | O5: =O4*O3 -> 4122720 | P5: =P4*P3 -> 4024560 | Q5: =Q4*Q3 -> 4662600 | S5: =SUM(E5:P5) -> 105688720
K6: sales discount | L6: =-(M4/409-1) -> 0.1198044
C7: Production Budget
C8: 45985 | D8: 46015 | E8: 45682 | F8: 45713 | G8: 45741 | H8: 45772 | I8: 45802 | J8: 45833 | K8: 45863 | L8: 45894 | M8: 45925 | N8: 45955 | O8: 45986 | P8: 46016 | Q8: Jan | R8: Feb
B9: Expected unit sales (from Sales Budget) | C9: =C11-C10 -> 8800 | D9: =D11-D10 -> 9720 | E9: =E11-E10 -> 10540 | F9: =F11-F10 -> 14280 | G9: =G11-G10 -> 22200 | H9: =H11-H10 -> 24900 | I9: =I11-I10 -> 29280 | J9: =J11-J10 -> 37260 | ... Q9: =Q11-Q10 -> 11400 | S9: =SUM(E9:P9) -> 263080
B10: ADD: Ending finished goods units | C10: =D13*0.2 -> 2000 | D10: =E13*0.2 -> 2280 | E10: =F13*0.2 -> 3140 | F10: =G13*0.2 -> 4560 | G10: =H13*0.2 -> 5160 | H10: =I13*0.2 -> 6060 | I10: =J13*0.2 -> 7080 | J10: =K13*0.2 -> 5220 | ... Q10: =R13*0.2 -> 3000 | S10: =P10 -> 2400
B11: Total required units | C11: =SUM(C13+C12) -> 10800 | D11: =SUM(D13+D12) -> 12000 | E11: =SUM(E13+E12) -> 13680 | F11: =SUM(F13+F12) -> 18840 | G11: =SUM(G13+G12) -> 27360 | H11: =SUM(H13+H12) -> 30960 | I11: =SUM(I13+I12) -> 36360 | J11: =SUM(J13+J12) -> 42480 | ... R11: =SUM(R13+R12) -> 18000 | S11: =S9+S10 -> 265480
B12: LESS: Beginning finished goods units | C12: =0.2*C13 -> 1800 | D12: =C10 -> 2000 | E12: =D10 -> 2280 | F12: =E10 -> 3140 | G12: =F10 -> 4560 | H12: =G10 -> 5160 | I12: =H10 -> 6060 | J12: =I10 -> 7080 | K12: =J10 -> 5220 | ... R12: =Q10 -> 3000 | S12: =E12 -> 2280
B13: Required production units (given) | C13: 9000 | D13: 10000 | E13: 11400 | F13: 15700 | G13: 22800 | H13: 25800 | I13: 30300 | J13: 35400 | K13: 26100 | L13: 25400 | M13: 35000 | N13: 15000 | O13: 10100 | P13: 10200 | Q13: 12000 | R13: 15000 | S13: =S11-S12 -> 263200
C15: Direct Materials Budget - Alloy Steel
C16: 45985 | D16: 46015 | E16: 45682 | F16: 45713 | G16: 45741 | H16: 45772 | I16: 45802 | J16: 45833 | K16: 45863 | L16: 45894 | M16: 45925 | N16: 45955 | O16: 45986 | P16: 46016 | Q16: Jan | R16: Feb
B17: Required Production in units | C17: =C13 -> 9000 | D17: =D13 -> 10000 | E17: =E13 -> 11400 | F17: =F13 -> 15700 | G17: =G13 -> 22800 | H17: =H13 -> 25800 | I17: =I13 -> 30300 | J17: =J13 -> 35400 | ... R17: =R13 -> 15000 | S17: =SUM(E17:P17) -> 263200
B18: Direct Matreial per unit (0.5 s/m) | C18: 0.5 | D18: 0.5 | E18: 0.5 | F18: 0.5 | G18: 0.5 | H18: 0.5 | I18: 0.5 | J18: 0.5 | K18: 0.5 | L18: 0.5 | M18: 0.5 | N18: 0.5 | O18: 0.5 | P18: 0.5 | Q18: 0.5 | R18: 0.5 | S18: 0.5
B19: Total req. for production | C19: =C17*C18 -> 4500 | D19: =D17*D18 -> 5000 | E19: =E17*E18 -> 5700 | F19: =F17*F18 -> 7850 | G19: =G17*G18 -> 11400 | H19: =H17*H18 -> 12900 | I19: =I17*I18 -> 15150 | J19: =J17*J18 -> 17700 | ... S19: =S17*S18 -> 131600
B20: End inventory | C20: =21%*D19 -> 1050 | D20: =21%*E19 -> 1197 | E20: =21%*F19 -> 1648.5 | F20: =21%*G19 -> 2394 | G20: =21%*H19 -> 2709 | H20: =21%*I19 -> 3181.5 | I20: =21%*J19 -> 3717 | J20: =21%*K19 -> 2740.5 | ... Q20: =21%*R19 -> 1575 | S20: =P20 -> 1260
B21: Total required | C21: =C19+C20 -> 5550 | D21: =D19+D20 -> 6197 | E21: =E19+E20 -> 7348.5 | F21: =F19+F20 -> 10244 | G21: =G19+G20 -> 14109 | H21: =H19+H20 -> 16081.5 | I21: =I19+I20 -> 18867 | J21: =J19+J20 -> 20440.5 | ... S21: =S19+S20 -> 132860
B22: Beginning inventory | D22: =C20 -> 1050 | E22: =D20 -> 1197 | F22: =E20 -> 1648.5 | G22: =F20 -> 2394 | H22: =G20 -> 2709 | I22: =H20 -> 3181.5 | J22: =I20 -> 3717 | K22: =J20 -> 2740.5 | ... R22: =Q20 -> 1575 | S22: =E22 -> 1197
B23: DM purchases | D23: =D21-D22 -> 5147 | E23: =E21-E22 -> 6151.5 | F23: =F21-F22 -> 8595.5 | G23: =G21-G22 -> 11715 | H23: =H21-H22 -> 13372.5 | I23: =I21-I22 -> 15685.5 | J23: =J21-J22 -> 16723.5 | K23: =K21-K22 -> 12976.5 | ... Q23: =Q21-Q22 -> 6315 | S23: =S21-S22 -> 131663
B24: Cost per DM unit ($) | C24: 46 | D24: 46 | E24: 46 | F24: 46 | G24: 46 | H24: 46 | I24: 46 | J24: 46 | K24: 46 | L24: 46 | M24: 46 | N24: 46 | O24: 46 | P24: 46 | Q24: 46 | S24: 46
B25: Total cost of purchases ($) | D25: =D24*D23 -> 236762 | E25: =E24*E23 -> 282969 | F25: =F24*F23 -> 395393 | G25: =G24*G23 -> 538890 | H25: =H24*H23 -> 615135 | I25: =I24*I23 -> 721533 | J25: =J24*J23 -> 769281 | K25: =K24*K23 -> 596919 | ... Q25: =Q24*Q23 -> 290490 | S25: =S23*S24 -> 6056498
C27: Direct Materials Budget - Plastic
C28: 45985 | D28: 46015 | E28: 45682 | F28: 45713 | G28: 45741 | H28: 45772 | I28: 45802 | J28: 45833 | K28: 45863 | L28: 45894 | M28: 45925 | N28: 45955 | O28: 45986 | P28: 46016 | Q28: Jan | R28: Feb
B29: Required Production in units | C29: =C13 -> 9000 | D29: =D13 -> 10000 | E29: =E13 -> 11400 | F29: =F13 -> 15700 | G29: =G13 -> 22800 | H29: =H13 -> 25800 | I29: =I13 -> 30300 | J29: =J13 -> 35400 | ... R29: =R13 -> 15000 | S29: =SUM(E29:P29) -> 263200
B30: Direct Matreial per unit (kg) | C30: 2 | D30: 2 | E30: 2 | F30: 2 | G30: 2 | H30: 2 | I30: 2 | J30: 2 | K30: 2 | L30: 2 | M30: 2 | N30: 2 | O30: 2 | P30: 2 | Q30: 2 | R30: 2 | S30: 2
B31: Total req. for production | C31: =C29*C30 -> 18000 | D31: =D29*D30 -> 20000 | E31: =E29*E30 -> 22800 | F31: =F29*F30 -> 31400 | G31: =G29*G30 -> 45600 | H31: =H29*H30 -> 51600 | I31: =I29*I30 -> 60600 | J31: =J29*J30 -> 70800 | ... S31: =S29*S30 -> 526400
B32: End inventory | C32: =21%*D31 -> 4200 | D32: =21%*E31 -> 4788 | E32: =21%*F31 -> 6594 | F32: =21%*G31 -> 9576 | G32: =21%*H31 -> 10836 | H32: =21%*I31 -> 12726 | I32: =21%*J31 -> 14868 | J32: =21%*K31 -> 10962 | ... Q32: =21%*R31 -> 6300 | S32: =P32 -> 5040
B33: Total required | C33: =C31+C32 -> 22200 | D33: =D31+D32 -> 24788 | E33: =E31+E32 -> 29394 | F33: =F31+F32 -> 40976 | G33: =G31+G32 -> 56436 | H33: =H31+H32 -> 64326 | I33: =I31+I32 -> 75468 | J33: =J31+J32 -> 81762 | ... S33: =S31+S32 -> 531440
B34: Beginning inventory | D34: =C32 -> 4200 | E34: =D32 -> 4788 | F34: =E32 -> 6594 | G34: =F32 -> 9576 | H34: =G32 -> 10836 | I34: =H32 -> 12726 | J34: =I32 -> 14868 | K34: =J32 -> 10962 | ... R34: =Q32 -> 6300 | S34: =E34 -> 4788
B35: DM purchases | D35: =D33-D34 -> 20588 | E35: =E33-E34 -> 24606 | F35: =F33-F34 -> 34382 | G35: =G33-G34 -> 46860 | H35: =H33-H34 -> 53490 | I35: =I33-I34 -> 62742 | J35: =J33-J34 -> 66894 | K35: =K33-K34 -> 51906 | ... Q35: =Q33-Q34 -> 25260 | S35: =S33-S34 -> 526652
B36: Cost per DM unit ($) | C36: 1.2 | D36: 1.2 | E36: 1.2 | F36: 1.2 | G36: 1.2 | H36: 1.2 | I36: 1.2 | J36: 1.2 | K36: 1.2 | L36: 1.2 | M36: 1.2 | N36: 1.2 | O36: 1.2 | P36: 1.2 | Q36: 1.2 | S36: 1.2
B37: Total cost of purchases ($) | D37: =D36*D35 -> 24705.6 | E37: =E36*E35 -> 29527.2 | F37: =F36*F35 -> 41258.4 | G37: =G36*G35 -> 56232 | H37: =H36*H35 -> 64188 | I37: =I36*I35 -> 75290.4 | J37: =J36*J35 -> 80272.8 | K37: =K36*K35 -> 62287.2 | ... Q37: =Q36*Q35 -> 30312 | S37: =S35*S36 -> 631982.4
C39: Direct Materials Budget - Assembly Kits
C40: 45985 | D40: 46015 | E40: 45682 | F40: 45713 | G40: 45741 | H40: 45772 | I40: 45802 | J40: 45833 | K40: 45863 | L40: 45894 | M40: 45925 | N40: 45955 | O40: 45986 | P40: 46016 | Q40: Jan | R40: Feb
B41: Required Production in units | C41: =C13 -> 9000 | D41: =D13 -> 10000 | E41: =E13 -> 11400 | F41: =F13 -> 15700 | G41: =G13 -> 22800 | H41: =H13 -> 25800 | I41: =I13 -> 30300 | J41: =J13 -> 35400 | ... R41: =R13 -> 15000 | S41: =SUM(E41:P41) -> 263200
B42: Direct Matreial per unit (kg) | C42: 1 | D42: 1 | E42: 1 | F42: 1 | G42: 1 | H42: 1 | I42: 1 | J42: 1 | K42: 1 | L42: 1 | M42: 1 | N42: 1 | O42: 1 | P42: 1 | Q42: 1 | R42: 1 | S42: 1
B43: Total req. for production | C43: =C41*C42 -> 9000 | D43: =D41*D42 -> 10000 | E43: =E41*E42 -> 11400 | F43: =F41*F42 -> 15700 | G43: =G41*G42 -> 22800 | H43: =H41*H42 -> 25800 | I43: =I41*I42 -> 30300 | J43: =J41*J42 -> 35400 | ... S43: =S41*S42 -> 263200
B44: End inventory | C44: 1531 | D44: 1531 | E44: 1531 | F44: 1531 | G44: 1531 | H44: 1531 | I44: 1531 | J44: 1531 | K44: 1531 | L44: 1531 | M44: 1531 | N44: 1531 | O44: 1531 | P44: 1531 | Q44: 1531 | R44: 1531 | S44: =P44 -> 1531
B45: Total required | C45: =C43+C44 -> 10531 | D45: =D43+D44 -> 11531 | E45: =E43+E44 -> 12931 | F45: =F43+F44 -> 17231 | G45: =G43+G44 -> 24331 | H45: =H43+H44 -> 27331 | I45: =I43+I44 -> 31831 | J45: =J43+J44 -> 36931 | ... S45: =S43+S44 -> 264731
B46: Beginning inventory | D46: =C44 -> 1531 | E46: =D44 -> 1531 | F46: =E44 -> 1531 | G46: =F44 -> 1531 | H46: =G44 -> 1531 | I46: =H44 -> 1531 | J46: =I44 -> 1531 | K46: =J44 -> 1531 | ... R46: =Q44 -> 1531 | S46: =E46 -> 1531
B47: DM purchases | D47: =D45-D46 -> 10000 | E47: =E45-E46 -> 11400 | F47: =F45-F46 -> 15700 | G47: =G45-G46 -> 22800 | H47: =H45-H46 -> 25800 | I47: =I45-I46 -> 30300 | J47: =J45-J46 -> 35400 | K47: =K45-K46 -> 26100 | ... Q47: =Q45-Q46 -> 12000 | S47: =S45-S46 -> 263200
B48: Cost per DM unit ($) | C48: 156 | D48: 156 | E48: 156 | F48: 156 | G48: 156 | H48: 156 | I48: 156 | J48: 156 | K48: 156 | L48: 156 | M48: 156 | N48: 156 | O48: 156 | P48: 156 | Q48: 156 | S48: 156
B49: Total cost of purchases ($) | D49: =D48*D47 -> 1560000 | E49: =E48*E47 -> 1778400 | F49: =F48*F47 -> 2449200 | G49: =G48*G47 -> 3556800 | H49: =H48*H47 -> 4024800 | I49: =I48*I47 -> 4726800 | J49: =J48*J47 -> 5522400 | K49: =K48*K47 -> 4071600 | ... Q49: =Q48*Q47 -> 1872000 | S49: =S48*S47 -> 41059200
C51: Direct Labour Budget (fabrication labour)
C52: 45985 | D52: 46015 | E52: 45682 | F52: 45713 | G52: 45741 | H52: 45772 | I52: 45802 | J52: 45833 | K52: 45863 | L52: 45894 | M52: 45925 | N52: 45955 | O52: 45986 | P52: 46016 | Q52: Jan | R52: Feb
B53: Production | C53: =C17 -> 9000 | D53: =D17 -> 10000 | E53: =E17 -> 11400 | F53: =F17 -> 15700 | G53: =G17 -> 22800 | H53: =H17 -> 25800 | I53: =I17 -> 30300 | J53: =J17 -> 35400 | ... R53: =R17 -> 15000 | S53: =SUM(E53:P53) -> 263200
B54: Hours per unit | C54: 2 | D54: 2 | E54: 2 | F54: 2 | G54: 2 | H54: 2 | I54: 2 | J54: 2 | K54: 2 | L54: 2 | M54: 2 | N54: 2 | O54: 2 | P54: 2 | Q54: 2 | R54: 2 | S54: 2
B55: Total hours | C55: =C54*C53 -> 18000 | D55: =D54*D53 -> 20000 | E55: =E54*E53 -> 22800 | F55: =F54*F53 -> 31400 | G55: =G54*G53 -> 45600 | H55: =H54*H53 -> 51600 | I55: =I54*I53 -> 60600 | J55: =J54*J53 -> 70800 | ... R55: =R54*R53 -> 30000 | S55: =S53*S54 -> 526400
B56: Cost per hour | C56: 20 | D56: 20 | E56: 20 | F56: 20 | G56: 20 | H56: 20 | I56: 20 | J56: 20 | K56: 20 | L56: 20 | M56: 20 | N56: 20 | O56: 20 | P56: 20 | Q56: 20 | R56: 20 | S56: 20
B57: Total cost of DL | C57: =C55*C56 -> 360000 | D57: =D55*D56 -> 400000 | E57: =E55*E56 -> 456000 | F57: =F55*F56 -> 628000 | G57: =G55*G56 -> 912000 | H57: =H55*H56 -> 1032000 | I57: =I55*I56 -> 1212000 | J57: =J55*J56 -> 1416000 | ... S57: =S55*S56 -> 10528000
C59: Direct Labour Budget (assembly labour)
C60: 45985 | D60: 46015 | E60: 45682 | F60: 45713 | G60: 45741 | H60: 45772 | I60: 45802 | J60: 45833 | K60: 45863 | L60: 45894 | M60: 45925 | N60: 45955 | O60: 45986 | P60: 46016 | Q60: Jan | R60: Feb
B61: Production | C61: =C17 -> 9000 | D61: =D17 -> 10000 | E61: =E17 -> 11400 | F61: =F17 -> 15700 | G61: =G17 -> 22800 | H61: =H17 -> 25800 | I61: =I17 -> 30300 | J61: =J17 -> 35400 | ... R61: =R17 -> 15000 | S61: =SUM(E61:P61) -> 263200
B62: Hours per unit | C62: 0.43 | D62: 0.43 | E62: 0.43 | F62: 0.43 | G62: 0.43 | H62: 0.43 | I62: 0.43 | J62: 0.43 | K62: 0.43 | L62: 0.43 | M62: 0.43 | N62: 0.43 | O62: 0.43 | P62: 0.43 | Q62: 0.43 | R62: 0.43 | S62: 0.43
B63: Total hours | C63: =C61*C62 -> 3870 | D63: =D61*D62 -> 4300 | E63: =E61*E62 -> 4902 | F63: =F61*F62 -> 6751 | G63: =G61*G62 -> 9804 | H63: =H61*H62 -> 11094 | I63: =I61*I62 -> 13029 | J63: =J61*J62 -> 15222 | ... R63: =R61*R62 -> 6450 | S63: =S62*S61 -> 113176
B64: Cost per hour | C64: 14 | D64: 14 | E64: 14 | F64: 14 | G64: 14 | H64: 14 | I64: 14 | J64: 14 | K64: 14 | L64: 14 | M64: 14 | N64: 14 | O64: 14 | P64: 14 | Q64: 14 | R64: 14 | S64: 14
B65: Total cost of DL | C65: =C63*C64 -> 54180 | D65: =D63*D64 -> 60200 | E65: =E63*E64 -> 68628 | F65: =F63*F64 -> 94514 | G65: =G63*G64 -> 137256 | H65: =H63*H64 -> 155316 | I65: =I63*I64 -> 182406 | J65: =J63*J64 -> 213108 | ... R65: =R63*R64 -> 90300 | S65: =S64*S63 -> 1584464
C67: MOH Budget
C68: 45985 | D68: 46015 | E68: 45682 | F68: 45713 | G68: 45741 | H68: 45772 | I68: 45802 | J68: 45833 | K68: 45863 | L68: 45894 | M68: 45925 | N68: 45955 | O68: 45986 | P68: 46016 | Q68: Jan | R68: Feb
B69: Fabrication Hours | C69: =C55 -> 18000 | D69: =D55 -> 20000 | E69: =E55 -> 22800 | F69: =F55 -> 31400 | G69: =G55 -> 45600 | H69: =H55 -> 51600 | I69: =I55 -> 60600 | J69: =J55 -> 70800 | ... R69: =R55 -> 30000
B70: Variable Costs
B71: Maintenance | C71: =0.4*C69 -> 7200 | D71: =0.4*D69 -> 8000 | E71: =0.4*E69 -> 9120 | F71: =0.4*F69 -> 12560 | G71: =0.4*G69 -> 18240 | H71: =0.4*H69 -> 20640 | I71: =0.4*I69 -> 24240 | J71: =0.4*J69 -> 28320 | ... R71: =0.4*R69 -> 12000 | S71: =SUM(E71:P71) -> 210560
B72: Utilities | C72: =0.7*C69 -> 12600 | D72: =0.7*D69 -> 14000 | E72: =0.7*E69 -> 15960 | F72: =0.7*F69 -> 21980 | G72: =0.7*G69 -> 31920 | H72: =0.7*H69 -> 36120 | I72: =0.7*I69 -> 42420 | J72: =0.7*J69 -> 49560 | ... R72: =0.7*R69 -> 21000 | S72: =SUM(E72:P72) -> 368480
B73: Indirect Materials | C73: =C69*1.2 -> 21600 | D73: =D69*1.2 -> 24000 | E73: =E69*1.2 -> 27360 | F73: =F69*1.2 -> 37680 | G73: =G69*1.2 -> 54720 | H73: =H69*1.2 -> 61920 | I73: =I69*1.2 -> 72720 | J73: =J69*1.2 -> 84960 | ... R73: =R69*1.2 -> 36000 | S73: =SUM(E73:P73) -> 631680
B74: Indirect Labour | C74: =C69*1.4 -> 25200 | D74: =D69*1.4 -> 28000 | E74: =E69*1.4 -> 31920 | F74: =F69*1.4 -> 43960 | G74: =G69*1.4 -> 63840 | H74: =H69*1.4 -> 72240 | I74: =I69*1.4 -> 84840 | J74: =J69*1.4 -> 99120 | ... R74: =R69*1.4 -> 42000 | S74: =SUM(E74:P74) -> 736960
B75: Total variable costs | C75: =SUM(C71:C74) -> 66600 | D75: =SUM(D71:D74) -> 74000 | E75: =SUM(E71:E74) -> 84360 | F75: =SUM(F71:F74) -> 116180 | G75: =SUM(G71:G74) -> 168720 | H75: =SUM(H71:H74) -> 190920 | I75: =SUM(I71:I74) -> 224220 | J75: =SUM(J71:J74) -> 261960 | ... R75: =SUM(R71:R74) -> 111000 | S75: =SUM(E75:P75) -> 1947680
B76: Fixed Costs
B77: Supervisor salaries | C77: 18779 | D77: 18779 | E77: 18779 | F77: 18779 | G77: 18779 | H77: 18779 | I77: 18779 | J77: 18779 | K77: 18779 | L77: 18779 | M77: 18779 | N77: 18779 | O77: 18779 | P77: 18779 | Q77: 18779 | R77: 18779 | S77: =SUM(E77:P77) -> 225348
B78: Depreciation | C78: 3671 | D78: 3671 | E78: 3671 | F78: 3671 | G78: 3671 | H78: 3671 | I78: 3671 | J78: 3671 | K78: 3671 | L78: 3671 | M78: 3671 | N78: 3671 | O78: 3671 | P78: 3671 | Q78: 3671 | R78: 3671 | S78: =SUM(E78:P78) -> 44052
B79: Taxes and insurance | C79: 8679 | D79: 8679 | E79: 8679 | F79: 8679 | G79: 8679 | H79: 8679 | I79: 8679 | J79: 8679 | K79: 8679 | L79: 8679 | M79: 8679 | N79: 8679 | O79: 8679 | P79: 8679 | Q79: 8679 | R79: 8679 | S79: =SUM(E79:P79) -> 104148
B80: Maintenance | C80: 5435 | D80: 5435 | E80: 5435 | F80: 5435 | G80: 5435 | H80: 5435 | I80: 5435 | J80: 5435 | K80: 5435 | L80: 5435 | M80: 5435 | N80: 5435 | O80: 5435 | P80: 5435 | Q80: 5435 | R80: 5435 | S80: =SUM(E80:P80) -> 65220
B81: Total fixed costs | C81: =SUM(C77:C80) -> 36564 | D81: =SUM(D77:D80) -> 36564 | E81: =SUM(E77:E80) -> 36564 | F81: =SUM(F77:F80) -> 36564 | G81: =SUM(G77:G80) -> 36564 | H81: =SUM(H77:H80) -> 36564 | I81: =SUM(I77:I80) -> 36564 | J81: =SUM(J77:J80) -> 36564 | ... R81: =SUM(R77:R80) -> 36564 | S81: =SUM(E81:P81) -> 438768
B82: Total MOH | C82: =C75+C81 -> 103164 | D82: =D75+D81 -> 110564 | E82: =E75+E81 -> 120924 | F82: =F75+F81 -> 152744 | G82: =G75+G81 -> 205284 | H82: =H75+H81 -> 227484 | I82: =I75+I81 -> 260784 | J82: =J75+J81 -> 298524 | ... R82: =R75+R81 -> 147564 | S82: =SUM(E82:P82) -> 2386448
C84: S&A Budget
C85: 45985 | D85: 46015 | E85: 45682 | F85: 45713 | G85: 45741 | H85: 45772 | I85: 45802 | J85: 45833 | K85: 45863 | L85: 45894 | M85: 45925 | N85: 45955 | O85: 45986 | P85: 46016 | Q85: Jan | R85: Feb
B86: Unit sales | C86: =C3 -> 8800 | D86: =D3 -> 9720 | E86: =E3 -> 10540 | F86: =F3 -> 14280 | G86: =G3 -> 22200 | H86: =H3 -> 24900 | I86: =I3 -> 29280 | J86: =J3 -> 37260 | ... Q86: =Q3 -> 11400
B87: Sales ($) | C87: =C5 -> 3599200 | D87: =D5 -> 3975480 | E87: =E5 -> 4310860 | F87: =F5 -> 5840520 | G87: =G5 -> 9079800 | H87: =H5 -> 10184100 | I87: =I5 -> 11975520 | J87: =J5 -> 15239340 | ... Q87: =Q5 -> 4662600
B88: Variable Costs
B89: Sales commisions | C89: =3%*C87 -> 107976 | D89: =3%*D87 -> 119264.4 | E89: =3%*E87 -> 129325.8 | F89: =3%*F87 -> 175215.6 | G89: =3%*G87 -> 272394 | H89: =3%*H87 -> 305523 | I89: =3%*I87 -> 359265.6 | J89: =3%*J87 -> 457180.2 | ... Q89: =3%*Q87 -> 139878 | S89: =SUM(E89:P89) -> 3170661.6
B90: Freight out | C90: =8*C86 -> 70400 | D90: =8*D86 -> 77760 | E90: =8*E86 -> 84320 | F90: =8*F86 -> 114240 | G90: =8*G86 -> 177600 | H90: =8*H86 -> 199200 | I90: =8*I86 -> 234240 | J90: =8*J86 -> 298080 | ... Q90: =8*Q86 -> 91200 | S90: =SUM(E90:P90) -> 2104640
B91: Total variable costs | C91: =SUM(C89:C90) -> 178376 | D91: =SUM(D89:D90) -> 197024.4 | E91: =SUM(E89:E90) -> 213645.8 | F91: =SUM(F89:F90) -> 289455.6 | G91: =SUM(G89:G90) -> 449994 | H91: =SUM(H89:H90) -> 504723 | I91: =SUM(I89:I90) -> 593505.6 | J91: =SUM(J89:J90) -> 755260.2 | ... Q91: =SUM(Q89:Q90) -> 231078 | S91: =SUM(E91:P91) -> 5275301.6
B92: Fixed costs
B93: Advertising | C93: 7500 | D93: 7500 | E93: 7500 | F93: 7500 | G93: 7500 | H93: 7500 | I93: 7500 | J93: 7500 | K93: 7500 | L93: 7500 | M93: 7500 | N93: 7500 | O93: 7500 | P93: 7500 | Q93: 7500 | S93: =SUM(E93:P93) -> 90000
B94: Sales salaries | C94: 17000 | D94: 17000 | E94: 17000 | F94: 17000 | G94: 17000 | H94: 17000 | I94: 17000 | J94: 17000 | K94: 17000 | L94: 17000 | M94: 17000 | N94: 17000 | O94: 17000 | P94: 17000 | Q94: 17000 | S94: =SUM(E94:P94) -> 204000
B95: Office salaries | C95: 7000 | D95: 7000 | E95: 7000 | F95: 7000 | G95: 7000 | H95: 7000 | I95: 7000 | J95: 7000 | K95: 7000 | L95: 7000 | M95: 7000 | N95: 7000 | O95: 7000 | P95: 7000 | Q95: 7000 | S95: =SUM(E95:P95) -> 84000
B96: Depreciation | C96: 712 | D96: 712 | E96: 712 | F96: 712 | G96: 712 | H96: 712 | I96: 712 | J96: 712 | K96: 712 | L96: 712 | M96: 712 | N96: 712 | O96: 712 | P96: 712 | Q96: 712 | S96: =SUM(E96:P96) -> 8544
B97: Property taxes | C97: 1000 | D97: 1000 | E97: 1000 | F97: 1000 | G97: 1000 | H97: 1000 | I97: 1000 | J97: 1000 | K97: 1000 | L97: 1000 | M97: 1000 | N97: 1000 | O97: 1000 | P97: 1000 | Q97: 1000 | S97: =SUM(E97:P97) -> 12000
B98: Total fixed costs | C98: =SUM(C93:C97) -> 33212 | D98: =SUM(D93:D97) -> 33212 | E98: =SUM(E93:E97) -> 33212 | F98: =SUM(F93:F97) -> 33212 | G98: =SUM(G93:G97) -> 33212 | H98: =SUM(H93:H97) -> 33212 | I98: =SUM(I93:I97) -> 33212 | J98: =SUM(J93:J97) -> 33212 | ... Q98: =SUM(Q93:Q97) -> 33212 | S98: =SUM(E98:P98) -> 398544
B99: Total S&A | C99: =C98+C91 -> 211588 | D99: =D98+D91 -> 230236.4 | E99: =E98+E91 -> 246857.8 | F99: =F98+F91 -> 322667.6 | G99: =G98+G91 -> 483206 | H99: =H98+H91 -> 537935 | I99: =I98+I91 -> 626717.6 | J99: =J98+J91 -> 788472.2 | ... Q99: =Q98+Q91 -> 264290 | S99: =SUM(E99:P99) -> 5673845.6
D102: Alloy steel | E102: plastic | F102: assembly kits | G102: total DM/unit
C103: DM/unit | D103: =0.5*46 -> 23 | E103: =2*1.2 -> 2.4 | F103: 156 | G103: =F103+E103+D103 -> 181.4
D105: fabrication | E105: assembly | G105: total DL/unit
C106: DL/unit | D106: =2*20 -> 40 | E106: =0.43*14 -> 6.02 | G106: =E106+D106 -> 46.02
D108: variable MOH/ unit | E108: Fixed MOH/unit | G108: Total MOH/unit
D109: =SUM(0.4,0.7,1.2,1.4)*2 -> 7.4 | E109: 1.6670517 | G109: =E109+D109 -> 9.0670517
C111: total fixed MOH | D111: =SUM(E81:P81) -> 438768 | F111: cost per unit | G111: =G109+G106+G103 -> 236.48705
C112: units produced | D112: =SUM(E13:P13) -> 263200
...

Sheet Cash Budget
B1: Collection schedule
B2: 45985 | C2: 46015 | D2: 45682 | E2: 45713 | F2: 45741 | G2: 45772 | H2: 45802 | I2: 45833 | J2: 45863 | K2: 45894 | L2: 45925 | M2: 45955 | N2: 45986 | O2: 46016 | P2: Jan | Q2: Feb
A3: Sales | B3: ='Operating Budgets'!C87 -> 3599200 | C3: ='Operating Budgets'!D87 -> 3975480 | D3: ='Operating Budgets'!E87 -> 4310860 | E3: ='Operating Budgets'!F87 -> 5840520 | F3: ='Operating Budgets'!G87 -> 9079800 | G3: ='Operating Budgets'!H87 -> 10184100 | H3: ='Operating Budgets'!I87 -> 11975520 | I3: ='Operating Budgets'!J87 -> 15239340 | ... P3: ='Operating Budgets'!Q87 -> 4662600
A4: 45985 | B4: =30%*B3 -> 1079760 | C4: =40%*B3 -> 1439680 | D4: =30%*B3 -> 1079760
A5: 46015 | C5: =30%*C3 -> 1192644 | D5: =40%*C3 -> 1590192 | E5: =30%*C3 -> 1192644
A6: 45682 | D6: =30%*D3 -> 1293258 | E6: =D3*40% -> 1724344 | F6: =D3*30% -> 1293258
A7: 45713 | E7: =E3*30% -> 1752156 | F7: =E3*40% -> 2336208 | G7: =E3*30% -> 1752156
A8: 45741 | F8: =F3*30% -> 2723940 | G8: =F3*40% -> 3631920 | H8: =F3*30% -> 2723940
A9: 45772 | G9: =G3*30% -> 3055230 | H9: =G3*40% -> 4073640 | I9: =G3*30% -> 3055230
A10: 45802 | H10: =H3*30% -> 3592656 | I10: =H3*40% -> 4790208 | J10: =H3*30% -> 3592656
A11: 45833 | I11: =I3*30% -> 4571802 | J11: =I3*40% -> 6095736 | K11: =I3*30% -> 4571802
A12: 45863 | J12: =J3*30% -> 3219648 | K12: =J3*40% -> 4292864 | L12: =J3*30% -> 3219648
A13: 45894 | K13: =K3*30% -> 2880996 | L13: =K3*40% -> 3841328 | M13: =K3*30% -> 2880996
A14: 45925 | L14: =L3*30% -> 4212000 | M14: =L3*40% -> 5616000 | N14: =L3*30% -> 4212000
A15: 45955 | M15: =M3*30% -> 1960746 | N15: =M3*40% -> 2614328 | O15: =M3*30% -> 1960746
A16: 45986 | N16: =N3*30% -> 1236816 | O16: =N3*40% -> 1649088 | P16: =N3*30% -> 1236816
A17: 46016 | O17: =O3*30% -> 1207368 | P17: =O3*40% -> 1609824 | Q17: =O3*30% -> 1207368
A18: Total Collections | B18: =SUM(B4:B17) -> 1079760 | C18: =SUM(C4:C17) -> 2632324 | D18: =SUM(D4:D17) -> 3963210 | E18: =SUM(E4:E17) -> 4669144 | F18: =SUM(F4:F17) -> 6353406 | G18: =SUM(G4:G17) -> 8439306 | H18: =SUM(H4:H17) -> 10390236 | I18: =SUM(I4:I17) -> 12417240 | ... Q18: =SUM(Q4:Q17) -> 1207368
B20: Payment schedule
B21: 45985 | C21: 46015 | D21: 45682 | E21: 45713 | F21: 45741 | G21: 45772 | H21: 45802 | I21: 45833 | J21: 45863 | K21: 45894 | L21: 45925 | M21: 45955 | N21: 45986 | O21: 46016 | P21: Jan | Q21: Feb
A22: Total DM purchases | C22: ='Operating Budgets'!D49+'Operating Budgets'!D37+'Operating Budgets'!D25 -> 1821467.6 | D22: ='Operating Budgets'!E49+'Operating Budgets'!E37+'Operating Budgets'!E25 -> 2090896.2 | E22: ='Operating Budgets'!F49+'Operating Budgets'!F37+'Operating Budgets'!F25 -> 2885851.4 | F22: ='Operating Budgets'!G49+'Operating Budgets'!G37+'Operating Budgets'!G25 -> 4151922 | G22: ='Operating Budgets'!H49+'Operating Budgets'!H37+'Operating Budgets'!H25 -> 4704123 | H22: ='Operating Budgets'!I49+'Operating Budgets'!I37+'Operating Budgets'!I25 -> 5523623.4 | I22: ='Operating Budgets'!J49+'Operating Budgets'!J37+'Operating Budgets'!J25 -> 6371953.8 | J22: ='Operating Budgets'!K49+'Operating Budgets'!K37+'Operating Budgets'!K25 -> 4730806.2 | ... P22: ='Operating Budgets'!Q49+'Operating Budgets'!Q37+'Operating Budgets'!Q25 -> 2192802
A24: 46015 | C24: =50%*C22 -> 910733.8 | D24: =C24 -> 910733.8
A25: 45682 | D25: =50%*D22 -> 1045448.1 | E25: =D25 -> 1045448.1
A26: 45713 | E26: =50%*E22 -> 1442925.7 | F26: =E26 -> 1442925.7
A27: 45741 | F27: =50%*F22 -> 2075961 | G27: =F27 -> 2075961
A28: 45772 | G28: =50%*G22 -> 2352061.5 | H28: =G28 -> 2352061.5
A29: 45802 | H29: =50%*H22 -> 2761811.7 | I29: =H29 -> 2761811.7
A30: 45833 | I30: =50%*I22 -> 3185976.9 | J30: =I30 -> 3185976.9
A31: 45863 | J31: =50%*J22 -> 2365403.1 | K31: =J31 -> 2365403.1
A32: 45894 | K32: =50%*K22 -> 2329383.2 | L32: =K32 -> 2329383.2
A33: 45925 | L33: =50%*L22 -> 3121160 | M33: =L33 -> 3121160
A34: 45955 | M34: =50%*M22 -> 1347431.7 | N34: =M34 -> 1347431.7
A35: 45986 | N35: =50%*N22 -> 916336.7 | O35: =N35 -> 916336.7
A36: 46016 | O36: =O22*50% -> 929940.6 | P36: =O36 -> 929940.6
A37: Total payments | C37: =SUM(C24:C36) -> 910733.8 | D37: =SUM(D24:D36) -> 1956181.9 | E37: =SUM(E24:E36) -> 2488373.8 | F37: =SUM(F24:F36) -> 3518886.7 | G37: =SUM(G24:G36) -> 4428022.5 | H37: =SUM(H24:H36) -> 5113873.2 | I37: =SUM(I24:I36) -> 5947788.6 | J37: =SUM(J24:J36) -> 5551380 | ... P37: =SUM(P24:P36) -> 929940.6
B39: Cash budget
B40: 45985 | C40: 46015 | D40: 45682 | E40: 45713 | F40: 45741 | G40: 45772 | H40: 45802 | I40: 45833 | J40: 45863 | K40: 45894 | L40: 45925 | M40: 45955 | N40: 45986 | O40: 46016 | P40: Total
A41: B. cash balance | D41: 95000 | E41: =D58 -> 1212668 | F41: =E58 -> 2198562.2 | G41: =F58 -> 3298385.2 | H41: =G58 -> 5359983.4 | I41: =H58 -> 8357488.2 | J41: =I58 -> 12113885 | K41: =J58 -> 17477672 | L41: =K58 -> 22629014 | ... O41: =N58 -> 35447815 | P41: =D41 -> 95000
A42: Cash receipts
A43: Collections | D43: =D18 -> 3963210 | E43: =E18 -> 4669144 | F43: =F18 -> 6353406 | G43: =G18 -> 8439306 | H43: =H18 -> 10390236 | I43: =I18 -> 12417240 | J43: =J18 -> 12908040 | K43: =K18 -> 11745662 | ... O43: =O18 -> 4817202 | P43: =SUM(D43:O43) -> 105497308
A44: Available cash | D44: =D41+D43 -> 4058210 | E44: =E41+E43 -> 5881812 | F44: =F41+F43 -> 8551968.2 | G44: =G41+G43 -> 11737691 | H44: =H41+H43 -> 15750219 | I44: =I41+I43 -> 20774728 | J44: =J41+J43 -> 25021925 | K44: =K41+K43 -> 29223334 | ... P44: =P41+P43 -> 105592308
A45: cash dispursments
A46: DM payments | D46: =D37 -> 1956181.9 | E46: =E37 -> 2488373.8 | F46: =F37 -> 3518886.7 | G46: =G37 -> 4428022.5 | H46: =H37 -> 5113873.2 | I46: =I37 -> 5947788.6 | J46: =J37 -> 5551380 | K46: =K37 -> 4694786.3 | ... O46: =O37 -> 1846277.3 | P46: =SUM(D46:O46) -> 47728474
A47: DL | D47: ='Operating Budgets'!E57+'Operating Budgets'!E65 -> 524628 | E47: ='Operating Budgets'!F57+'Operating Budgets'!F65 -> 722514 | F47: ='Operating Budgets'!G57+'Operating Budgets'!G65 -> 1049256 | G47: ='Operating Budgets'!H57+'Operating Budgets'!H65 -> 1187316 | H47: ='Operating Budgets'!I57+'Operating Budgets'!I65 -> 1394406 | I47: ='Operating Budgets'!J57+'Operating Budgets'!J65 -> 1629108 | J47: ='Operating Budgets'!K57+'Operating Budgets'!K65 -> 1201122 | K47: ='Operating Budgets'!L57+'Operating Budgets'!L65 -> 1168908 | ... O47: ='Operating Budgets'!P57+'Operating Budgets'!P65 -> 469404 | P47: =SUM(D47:O47) -> 12112464
A48: MOH | D48: ='Operating Budgets'!E82-'Operating Budgets'!E78 -> 117253 | E48: ='Operating Budgets'!F82-'Operating Budgets'!F78 -> 149073 | F48: ='Operating Budgets'!G82-'Operating Budgets'!G78 -> 201613 | G48: ='Operating Budgets'!H82-'Operating Budgets'!H78 -> 223813 | H48: ='Operating Budgets'!I82-'Operating Budgets'!I78 -> 257113 | I48: ='Operating Budgets'!J82-'Operating Budgets'!J78 -> 294853 | J48: ='Operating Budgets'!K82-'Operating Budgets'!K78 -> 226033 | K48: ='Operating Budgets'!L82-'Operating Budgets'!L78 -> 220853 | ... O48: ='Operating Budgets'!P82-'Operating Budgets'!P78 -> 108373 | P48: =SUM(D48:O48) -> 2342396
A49: S&A | D49: ='Operating Budgets'!E99-'Operating Budgets'!E96 -> 246145.8 | E49: ='Operating Budgets'!F99-'Operating Budgets'!F96 -> 321955.6 | F49: ='Operating Budgets'!G99-'Operating Budgets'!G96 -> 482494 | G49: ='Operating Budgets'!H99-'Operating Budgets'!H96 -> 537223 | H49: ='Operating Budgets'!I99-'Operating Budgets'!I96 -> 626005.6 | I49: ='Operating Budgets'!J99-'Operating Budgets'!J96 -> 787760.2 | J49: ='Operating Budgets'!K99-'Operating Budgets'!K96 -> 564384.8 | K49: ='Operating Budgets'!L99-'Operating Budgets'!L96 -> 508439.6 | ... O49: ='Operating Budgets'!P99-'Operating Budgets'!P96 -> 231956.8 | P49: =SUM(D49:O49) -> 5665301.6
A50: Dividends | M50: 120000 | P50: =SUM(D50:O50) -> 120000
A51: Total dispursements | D51: =SUM(D46:D50) -> 2844208.7 | E51: =SUM(E46:E50) -> 3681916.4 | F51: =SUM(F46:F50) -> 5252249.7 | G51: =SUM(G46:G50) -> 6376374.5 | H51: =SUM(H46:H50) -> 7391397.8 | I51: =SUM(I46:I50) -> 8659509.8 | J51: =SUM(J46:J50) -> 7542919.8 | K51: =SUM(K46:K50) -> 6592986.9 | ... P51: =SUM(P46:P50) -> 67968635
A52: Excess (deficiency) | D52: =D44-D51 -> 1214001.3 | E52: =E44-E51 -> 2199895.6 | F52: =F44-F51 -> 3299718.5 | G52: =G44-G51 -> 5361316.7 | H52: =H44-H51 -> 8358821.6 | I52: =I44-I51 -> 12115218 | J52: =J44-J51 -> 17479005 | K52: =K44-K51 -> 22630347 | ... P52: =P44-P51 -> 37623673
A53: Financing
A54: Borrowing
A55: Repayment | O55: =-(200000*11%) -> -22000 | P55: =-(200000*11%) -> -22000
A56: Interest | D56: =-(200000*8%/12) -> -1333.3333 | E56: =-(200000*8%/12) -> -1333.3333 | F56: =-(200000*8%/12) -> -1333.3333 | G56: =-(200000*8%/12) -> -1333.3333 | H56: =-(200000*8%/12) -> -1333.3333 | I56: =-(200000*8%/12) -> -1333.3333 | J56: =-(200000*8%/12) -> -1333.3333 | K56: =-(200000*8%/12) -> -1333.3333 | ... O56: =-(200000*8%/12) -> -1333.3333 | P56: =SUM(D56:O56) -> -16000
A58: Ending Cash Balance | D58: =SUM(D52:D56) -> 1212668 | E58: =SUM(E52:E56) -> 2198562.2 | F58: =SUM(F52:F56) -> 3298385.2 | G58: =SUM(G52:G56) -> 5359983.4 | H58: =SUM(H52:H56) -> 8357488.2 | I58: =SUM(I52:I56) -> 12113885 | J58: =SUM(J52:J56) -> 17477672 | K58: =SUM(K52:K56) -> 22629014 | ... P58: =SUM(P52:P56) -> 37585673

Sheet Balance Sheet
A1: Escooter Inc.
A2: Balance Sheet
A3: As at Dec, 2025
A4: Assets
A5: Cash | E5: ='Cash Budget'!P58 -> 37585673
A6: Accounts Receivable | E6: =SUM('Cash Budget'!P16,'Cash Budget'!P17,'Cash Budget'!Q17) -> 4054008
A7: Raw materials inventory
A8: Alloy steel | D8: ='Operating Budgets'!S20*'Operating Budgets'!S24 -> 57960
A9: Plastic | D9: ='Operating Budgets'!S32*'Operating Budgets'!S36 -> 6048
A10: Assembly kits | D10: ='Operating Budgets'!S44*'Operating Budgets'!S48 -> 238836 | E10: =SUM(D8:D10) -> 302844
A11: Finished good inventory | E11: ='Operating Budgets'!S10*'Operating Budgets'!G111 -> 567568.92
A12: Property, plant and equipment | E12: =420000-I12 -> 367404 | H12: Depreciation | I12: ='Operating Budgets'!S78+'Operating Budgets'!S96 -> 52596 | K12: Alloy steel | L12: ='Operating Budgets'!E22*'Operating Budgets'!E24 -> 55062
A13: Total assets | E13: =SUM(E5:E12) -> 42877498 | K13: Plastic | L13: ='Operating Budgets'!E34*'Operating Budgets'!E36 -> 5745.6
K14: Assembly kits | L14: ='Operating Budgets'!E46*'Operating Budgets'!E48 -> 238836
A15: Liabilities and Shareholders equity
A16: Accounts payable | E16: ='Cash Budget'!P36 -> 929940.6
A17: Long term note | E17: =200000+'Cash Budget'!O55 -> 178000
A18: Common shares | E18: 600000
A19: Retained earnings | E19: =I30 -> 41169557 | H19: Beg cash balance | I19: 95000
A20: Total liabilities and SE | E20: =SUM(E16:E19) -> 42877498 | H20: beg A.R | I20: ='Cash Budget'!D4+'Cash Budget'!D5+'Cash Budget'!E5 -> 3862596
H21: beg F.G | I21: ='Operating Budgets'!E12*'Operating Budgets'!G111 -> 539190.48
H22: beg raw materials | I22: =SUM(L12:L14) -> 299643.6
H23: PPE | I23: 420000
H24: beg A/P | I24: =-'Cash Budget'!D24 -> -910733.8
H25: beg LT liab | I25: -200000
H26: beg common shares | I26: -600000
G27: = | H27: beg R.E | I27: =SUM(I19:I26) -> 3505696.3
H28: net income | I28: ='Operating Budgets'!G126 -> 37783861
H29: dividends | I29: =-'Cash Budget'!P50 -> -120000
H30: Ending R.E | I30: =SUM(I27:I29) -> 41169557
H33: ='Operating Budgets'!S82/'Operating Budgets'!S55 -> 4.5335258 | I33: Q.24
